genro_treestore/__init__.py
genro_treestore/exceptions.py
genro_treestore/py.typed
genro_treestore/validation.py
genro_treestore/builders/__init__.py
genro_treestore/builders/base.py
genro_treestore/builders/decorators.py
genro_treestore/builders/html.py
genro_treestore/builders/rnc/README.md
genro_treestore/builders/rnc/__init__.py
genro_treestore/builders/rnc/rnc_parser.py
genro_treestore/builders/rnc/rnc_schema.py
genro_treestore/builders/xsd/README.md
genro_treestore/builders/xsd/__init__.py
genro_treestore/builders/xsd/xsd_schema.py
genro_treestore/resolvers/__init__.py
genro_treestore/resolvers/base.py
genro_treestore/resolvers/directory.py
genro_treestore/store/__init__.py
genro_treestore/store/core.py
genro_treestore/store/loading.py
genro_treestore/store/node.py
genro_treestore/store/serialization.py
genro_treestore/store/subscription.py
genro_treestore-0.2.0.dist-info/METADATA
genro_treestore-0.2.0.dist-info/WHEEL
genro_treestore-0.2.0.dist-info/licenses/LICENSE
genro_treestore-0.2.0.dist-info/licenses/NOTICE
genro_treestore-0.2.0.dist-info/RECORD
