Metadata-Version: 2.4
Name: genro-treestore
Version: 0.2.0
Summary: Hierarchical data structures with builder pattern support for Genro Kyō
Project-URL: Repository, https://github.com/genropy/genro-treestore
Project-URL: Documentation, https://genro-treestore.readthedocs.io/
Author: Genropy Team
License-Expression: Apache-2.0
License-File: LICENSE
License-File: NOTICE
Keywords: builder,genro,hierarchical,tree,treestore
Classifier: Development Status :: 4 - Beta
Classifier: Intended Audience :: Developers
Classifier: License :: OSI Approved :: Apache Software License
Classifier: Operating System :: OS Independent
Classifier: Programming Language :: Python :: 3
Classifier: Programming Language :: Python :: 3 :: Only
Classifier: Topic :: Software Development :: Libraries :: Python Modules
Classifier: Topic :: Utilities
Requires-Python: >=3.10
Requires-Dist: genro-toolbox>=0.1.0
Provides-Extra: dev
Requires-Dist: ruff>=0.1.0; extra == 'dev'
Provides-Extra: docs
Requires-Dist: myst-parser>=4.0.0; extra == 'docs'
Requires-Dist: sphinx-autodoc-typehints>=3.0.0; extra == 'docs'
Requires-Dist: sphinx-rtd-theme>=3.0.0; extra == 'docs'
Requires-Dist: sphinx>=8.0.0; extra == 'docs'
Requires-Dist: sphinxcontrib-mermaid>=1.0.0; extra == 'docs'
Provides-Extra: test
Requires-Dist: genro-tytx[msgpack]>=0.1.0; extra == 'test'
Requires-Dist: pytest-cov>=4.0.0; extra == 'test'
Requires-Dist: pytest>=8.0.0; extra == 'test'
